{
  "name": "Mabelle Zimmerman",
  "age": 22,
  "address": {
    "street": "Vopoz Terrace",
    "city": "Kiwonav",
    "state": "WV",
    "zip": "83430"
  },
  "contact": {
    "phone": "(419) 945-1741",
    "servicePhone": "800376395"
  },
  "birthday": "1989-03-20T04:06:38.424Z",
  "ip": "227.44.160.36",
  "foo": "bar",
  "profile": {
    "about": "Waw lac naiju batetu gak anulacu kor menpuji he womzen av jikfaowa. Kehdahob okotogec pekasfa tepocam wopi gil cotekivo upseb arewu vew sijtel cifas. Sizo mi tadkuwuc ad luzep rifmiaw ri tujbes zow ig do uji raznohkah po zojmenos pufoci.",
    "bio": "Ikduti firnirruw huz fefbipat hej ep jibmeh ecbis pu ulovbaz izca ikcof imibi gu ur zohezo. Kucogmek efeworu kar lagi jaguk mekac ja gednafu utsi mavos mec befkopke jati zagfos haja joganjor gaabu. Oj zig nugu we ri vowbusi at ajsivoh eb ziraaw venafvi ka tolsuwam tumjeddo."
  },
  "apiKey": "218f9dfdd68adb7de1adafeba7544852693dd0af2e6704c7012cd0e9bc93e793",
  "currency": {
    "code": "HNL",
    "name": "Honduras Lempira"
  }
}